Workbook

Sheet Assumptions
B2: Traffic Machine — Assumptions (2-Phase Model)
B3: NinfraEU | Phase 1: Creator/Agency (Apr–Jun) → Phase 2: SaaS (Jul+)
B5: → P&L & Runway | C5: → Scenarios
B7: PHASE 1 — CREATOR/AGENCY REVENUE (Apr–Jun 2026)
B8: Assumption | C8: Value | D8: Rationale
B9: Creator accounts managed | C9: 3 | D9: Start with 2-3 creators. Manageable solo while building/testing the tool.
B10: Avg gross revenue per creator (€/mo) | C10: 1500 | D10: Mid-tier creators. Conservative — top creators do 5-10x this. Ramps with traffic.
B11: Your revenue share (%) | C11: 0.25 | D11: 25% management fee is standard for creator agencies. Some charge 30-50%.
B12: Month 1 ramp (% of full capacity) | C12: 0.4 | D12: 40% — onboarding creators, setting up funnels. Tool is still being tested.
B13: Month 2 ramp | C13: 0.7 | D13: 70% — funnels active, traffic growing, creator content optimized.
B14: Month 3 ramp | C14: 1 | D14: 100% — full capacity. Traffic Machine is working, creators producing.
B15: Platform fees (OF/payment %) | C15: 0.2 | D15: OnlyFans takes 20%. This reduces the gross pool before your share.
B16: Target monthly income (full capacity) | C16: =C9*C10*(1-C15)*C11 -> 900
B18: PHASE 2 — SaaS REVENUE (Jul 2026+, for reference)
B19: Assumption | C19: Value | D19: Rationale
B20: SaaS price (€/user/month) | C20: 49 | D20: Mid-range creator SaaS. Competitive with Metricool/Taplio at €29-79/mo.
B21: Starting paying users at SaaS launch | C21: 5 | D21: First customers from your creator network. They've seen the tool work.
B22: Monthly user growth rate | C22: 0.3 | D22: 30% MoM — more realistic than 40% since you'll have product proof.
B23: Monthly churn rate | C23: 0.08 | D23: 8% — lower than typical early-stage because product is already tested.
B24: Expected SaaS launch | C24: Jul 2026 | D24: After 3-month Phase 1 test. Could be earlier if product proves out fast.
B26: COSTS (monthly, both phases)
B27: Cost Item | C27: €/month | D27: Rationale
B28: VPS / Hosting (Docker stack) | C28: 80 | D28: Hetzner/Contabo VPS. FastAPI + DB + containers. Scales to ~500 users.
B29: API costs (OpenAI, AI services) | C29: 150 | D29: GPT-4 API for content intelligence. Usage-based, scales with activity.
B30: SaaS tools (GitHub, monitoring, email) | C30: 50 | D30: GitHub Pro, Sentry, Mailgun/Resend, analytics. Essential dev/ops.
B31: Domain + CDN + SSL | C31: 15 | D31: Domain registration, Cloudflare. Minimal fixed cost.
B32: Marketing & content (ads, tools) | C32: 100 | D32: LinkedIn/social ads, content tools. Organic-first; this is the floor.
B33: Legal / accounting (amortized) | C33: 50 | D33: Quarterly accountant + compliance, averaged monthly.
B34: Personal allocation (founder draw) | C34: 300 | D34: Below minimum wage — reinvesting time. Covers essentials only.
B35: TOTAL FIXED MONTHLY COSTS | C35: =SUM(C28:C34) -> 745
B37: CASH & PAYMENT PROCESSING
B38: Item | C38: Value | D38: Notes
B39: Starting cash (April 2026) | C39: 2000 | D39: Available cash to fund operations. Adjust to your actual position.
B40: Additional monthly income (outside TM) | C40: 0 | D40: Any side income not from Traffic Machine. Set to 0 if none.

Sheet P&L & Runway
B2: Traffic Machine — P&L & Runway (Phase 1: Creator/Agency)
B3: Apr–Jun 2026 | Blue = input | Black = formula | Green = cross-sheet
B4: ← Assumptions | C4: → Scenarios
C6: Apr 2026 | D6: May 2026 | E6: Jun 2026 | F6: TOTAL
B7: CREATOR/AGENCY REVENUE
B8: Creators managed | C8: =Assumptions!C9 -> 3 | D8: =Assumptions!C9 -> 3 | E8: =Assumptions!C9 -> 3
B9: Avg gross revenue / creator | C9: =Assumptions!C10 -> 1500 | D9: =Assumptions!C10 -> 1500 | E9: =Assumptions!C10 -> 1500
B10: Ramp factor (capacity %) | C10: =Assumptions!C12 -> 0.4 | D10: =Assumptions!C13 -> 0.7 | E10: =Assumptions!C14 -> 1
B11: Total gross creator revenue | C11: =C8*C9*C10 -> 1800 | D11: =D8*D9*D10 -> 3150 | E11: =E8*E9*E10 -> 4500 | F11: =SUM(C11:E11) -> 9450
B12: - Platform fees (OF 20%) | C12: =-C11*Assumptions!C15 -> -360 | D12: =-D11*Assumptions!C15 -> -630 | E12: =-E11*Assumptions!C15 -> -900 | F12: =SUM(C12:E12) -> -1890
B13: Net creator revenue (after platform) | C13: =C11+C12 -> 1440 | D13: =D11+D12 -> 2520 | E13: =E11+E12 -> 3600 | F13: =SUM(C13:E13) -> 7560
B14: YOUR REVENUE (agency share) | C14: =C13*Assumptions!C11 -> 360 | D14: =D13*Assumptions!C11 -> 630 | E14: =E13*Assumptions!C11 -> 900 | F14: =SUM(C14:E14) -> 1890
B15: Other income | C15: =Assumptions!C40 -> 0 | D15: =Assumptions!C40 -> 0 | E15: =Assumptions!C40 -> 0 | F15: =SUM(C15:E15) -> 0
B16: TOTAL REVENUE | C16: =C14+C15 -> 360 | D16: =D14+D15 -> 630 | E16: =E14+E15 -> 900 | F16: =F14+F15 -> 1890
B18: COSTS (OPEX)
B19: VPS / Hosting | C19: =Assumptions!C28 -> 80 | D19: =Assumptions!C28 -> 80 | E19: =Assumptions!C28 -> 80 | F19: =SUM(C19:E19) -> 240
B20: API costs (OpenAI, AI) | C20: =Assumptions!C29 -> 150 | D20: =Assumptions!C29 -> 150 | E20: =Assumptions!C29 -> 150 | F20: =SUM(C20:E20) -> 450
B21: SaaS tools | C21: =Assumptions!C30 -> 50 | D21: =Assumptions!C30 -> 50 | E21: =Assumptions!C30 -> 50 | F21: =SUM(C21:E21) -> 150
B22: Domain + CDN | C22: =Assumptions!C31 -> 15 | D22: =Assumptions!C31 -> 15 | E22: =Assumptions!C31 -> 15 | F22: =SUM(C22:E22) -> 45
B23: Marketing & content | C23: =Assumptions!C32 -> 100 | D23: =Assumptions!C32 -> 100 | E23: =Assumptions!C32 -> 100 | F23: =SUM(C23:E23) -> 300
B24: Legal / accounting | C24: =Assumptions!C33 -> 50 | D24: =Assumptions!C33 -> 50 | E24: =Assumptions!C33 -> 50 | F24: =SUM(C24:E24) -> 150
B25: Personal allocation | C25: =Assumptions!C34 -> 300 | D25: =Assumptions!C34 -> 300 | E25: =Assumptions!C34 -> 300 | F25: =SUM(C25:E25) -> 900
B26: TOTAL COSTS | C26: =SUM(C19:C25) -> 745 | D26: =SUM(D19:D25) -> 745 | E26: =SUM(E19:E25) -> 745 | F26: =SUM(F19:F25) -> 2235
B28: BOTTOM LINE & RUNWAY
B29: NET INCOME (Loss) | C29: =C16-C26 -> -385 | D29: =D16-D26 -> -115 | E29: =E16-E26 -> 155 | F29: =F16-F26 -> -345
B30: Net margin % | C30: =IF(C16=0,0,C29/C16) -> -1.0694444 | D30: =IF(D16=0,0,D29/D16) -> -0.18253968 | E30: =IF(E16=0,0,E29/E16) -> 0.17222222 | F30: =IF(F16=0,0,F29/F16) -> -0.18253968
B32: CASH BALANCE (end of month) | C32: =Assumptions!C39+C29 -> 1615 | D32: =C32+D29 -> 1500 | E32: =D32+E29 -> 1655 | F32: =E32 -> 1655
B33: RUNWAY (months remaining) | C33: =IF(C29>=0,99,IF(C32<=0,0,C32/(-C29))) -> 4.1948052 | D33: =IF(D29>=0,99,IF(D32<=0,0,D32/(-D29))) -> 13.043478 | E33: =IF(E29>=0,99,IF(E32<=0,0,E32/(-E29))) -> 99
B34: Monthly burn (if losing money) | C34: =IF(C29<0,-C29,0) -> 385 | D34: =IF(D29<0,-D29,0) -> 115 | E34: =IF(E29<0,-E29,0) -> 0 | F34: =SUM(C34:E34) -> 500
B35: Revenue needed to breakeven | C35: =C26 -> 745 | D35: =D26 -> 745 | E35: =E26 -> 745
B36: Revenue vs breakeven (%) | C36: =IF(C26=0,0,C16/C26) -> 0.48322148 | D36: =IF(D26=0,0,D16/D26) -> 0.84563758 | E36: =IF(E26=0,0,E16/E26) -> 1.2080537
B38: Phase 1 uses Traffic Machine internally to manage creators and earn agency revenue. No SaaS customers yet.
B39: Change blue values on Assumptions to run scenarios. All formulas auto-update.
B40: Generated: 2026-03-17 | NinfraEU / Traffic Machine

Sheet Scenarios
B2: Traffic Machine — Scenario Comparison (Phase 1)
B3: What-if: Slow Start / Base Case / Strong Start
B4: ← Assumptions | C4: ← P&L & Runway
B6: Parameter | C6: Slow Start | D6: Base Case | E6: Strong Start
B7: Creators managed | C7: 2 | D7: 3 | E7: 5
B8: Avg gross rev / creator (€/mo) | C8: 800 | D8: 1500 | E8: 2500
B9: Your revenue share (%) | C9: 0.2 | D9: 0.25 | E9: 0.3
B10: Platform fees (%) | C10: 0.2 | D10: 0.2 | E10: 0.2
B11: Month 1 ramp (%) | C11: 0.25 | D11: 0.4 | E11: 0.6
B12: Month 2 ramp (%) | C12: 0.5 | D12: 0.7 | E12: 0.85
B13: Month 3 ramp (%) | C13: 0.75 | D13: 1 | E13: 1
B14: Monthly fixed costs | C14: 745 | D14: 745 | E14: 745
B15: Starting cash | C15: 2000 | D15: 2000 | E15: 2000
B17: 3-MONTH PROJECTED OUTCOMES
B18: Metric | C18: Slow Start | D18: Base Case | E18: Strong Start
B19: Month 1 revenue | C19: =C7*C8*(1-C10)*C9*C11 -> 64 | D19: =D7*D8*(1-D10)*D9*D11 -> 360 | E19: =E7*E8*(1-E10)*E9*E11 -> 1800
B20: Month 2 revenue | C20: =C7*C8*(1-C10)*C9*C12 -> 128 | D20: =D7*D8*(1-D10)*D9*D12 -> 630 | E20: =E7*E8*(1-E10)*E9*E12 -> 2550
B21: Month 3 revenue | C21: =C7*C8*(1-C10)*C9*C13 -> 192 | D21: =D7*D8*(1-D10)*D9*D13 -> 900 | E21: =E7*E8*(1-E10)*E9*E13 -> 3000
B22: Total 3-month revenue | C22: =C19+C20+C21 -> 384 | D22: =D19+D20+D21 -> 1890 | E22: =E19+E20+E21 -> 7350
B23: Total 3-month costs | C23: =C14*3 -> 2235 | D23: =D14*3 -> 2235 | E23: =E14*3 -> 2235
B24: Net income (3 months) | C24: =C22-C23 -> -1851 | D24: =D22-D23 -> -345 | E24: =E22-E23 -> 5115
B25: Cash at end of Month 3 | C25: =C15+C24 -> 149 | D25: =D15+D24 -> 1655 | E25: =E15+E24 -> 7115
B26: Avg monthly net income | C26: =C24/3 -> -617 | D26: =D24/3 -> -115 | E26: =E24/3 -> 1705
B27: Months to breakeven (from Month 1) | C27: =IF(C21>=C14,"Already there",IF(C21=0,"Never",ROUND(C14/C21*3,1)&" months")) -> 11.6 months | D27: =IF(D21>=D14,"Already there",IF(D21=0,"Never",ROUND(D14/D21*3,1)&" months")) -> Already there | E27: =IF(E21>=E14,"Already there",IF(E21=0,"Never",ROUND(E14/E21*3,1)&" months")) -> Already there
B30: Phase 1 strategy: Use Traffic Machine to manage creators, earn agency revenue, and battle-test the product.
B31: Base case: 3 creators at €1,500 gross, 25% share = €900/mo at full capacity. Costs: €745. Near breakeven by Month 3.
B32: Strong start: 5 creators at €2,500 = €2,250/mo at full. Profitable from Month 1. This funds Phase 2 SaaS development.
B33: Slow start: 2 creators at €800 = only €240/mo at full. Cash runs out. You need at least the base case to survive.
B34: Key lever: Number of creators and their revenue quality. 1 extra good creator changes everything.
B35: Phase 2 trigger: When Traffic Machine is proven (Month 3+), launch SaaS at €49/mo to other agencies/creators.
B37: Generated: 2026-03-17 | NinfraEU / Traffic Machine
